minecraft_assets
