Metadata-Version: 2.2
Name: mc-assets
Version: 1.13.0rc0
Summary: Minecraft Assets tracking PrismarineJS/minecraft-assets
Author-email: hunter <huntcsg@gmail.com>
License: MIT License
Project-URL: Homepage, https://github.com/mc-bench/mc-assets
Project-URL: Repository, https://github.com/mc-bench/mc-assets.git
Project-URL: Issues, https://github.com/mc-bench/mc-assets/issues
Requires-Python: <3.14,>=3.9
License-File: LICENSE
Provides-Extra: dev
Requires-Dist: ruff>=0.3.0; extra == "dev"
Requires-Dist: mypy>=1.8.0; extra == "dev"
Requires-Dist: pytest>=8.0.0; extra == "dev"
Requires-Dist: pytest-cov>=4.1.0; extra == "dev"
Requires-Dist: build>=1.0.0; extra == "dev"
